google/__init__.py
google/cloud/__init__.py
google/cloud/sqlcommenter/__init__.py
google/cloud/sqlcommenter/fastapi.py
google/cloud/sqlcommenter/flask.py
google/cloud/sqlcommenter/opencensus.py
google/cloud/sqlcommenter/opentelemetry.py
google/cloud/sqlcommenter/django/__init__.py
google/cloud/sqlcommenter/django/middleware.py
google/cloud/sqlcommenter/psycopg2/__init__.py
google/cloud/sqlcommenter/psycopg2/extension.py
google/cloud/sqlcommenter/sqlalchemy/__init__.py
google/cloud/sqlcommenter/sqlalchemy/executor.py
tests/django/__init__.py
tests/django/app_urls.py
tests/django/models.py
tests/django/settings.py
tests/django/tests.py
tests/django/urls.py
tests/django/views.py
tests/fastapi/__init__.py
tests/fastapi/app.py
tests/fastapi/tests.py
tests/flask/__init__.py
tests/flask/app.py
tests/flask/tests.py
tests/generic/__init__.py
tests/generic/test_add_sql_comment.py
tests/generic/test_generate_sql_comment.py
tests/generic/test_opencensus.py
tests/generic/test_opentelemetry.py
tests/psycopg2/__init__.py
tests/psycopg2/tests.py
tests/sqlalchemy/__init__.py
tests/sqlalchemy/tests.py
google_cloud_sqlcommenter_with_celery-1.0.0.dist-info/METADATA
google_cloud_sqlcommenter_with_celery-1.0.0.dist-info/WHEEL
google_cloud_sqlcommenter_with_celery-1.0.0.dist-info/top_level.txt
google_cloud_sqlcommenter_with_celery-1.0.0.dist-info/RECORD
