Metadata-Version: 2.1
Name: google-cloud-sqlcommenter-with-celery
Version: 1.0.0
Summary: sqlcommenter + annotation for celery tasks
Home-page: https://github.com/YashKumarVerma/sqlcommenter
Author: Yash Verma
Author-email: yk.verma2000@gmail.com
License: BSD
Platform: UNKNOWN
Classifier: Development Status :: 4 - Beta
Classifier: Environment :: Web Environment
Classifier: Intended Audience :: Developers
Classifier: License :: OSI Approved :: BSD License
Classifier: Operating System :: OS Independent
Classifier: Programming Language :: Python :: 3
Classifier: Programming Language :: Python :: 3.6
Classifier: Programming Language :: Python :: 3.7
Classifier: Programming Language :: Python :: 3.8
Classifier: Programming Language :: Python :: 3.9
Classifier: Topic :: Utilities
Classifier: Framework :: Django
Classifier: Framework :: Django :: 2.1
Classifier: Framework :: Django :: 2.2
Requires-Dist: asgiref
Requires-Dist: fastapi
Provides-Extra: django
Requires-Dist: django>=1.11; extra == "django"
Provides-Extra: fastapi
Requires-Dist: fastapi; extra == "fastapi"
Provides-Extra: flask
Requires-Dist: flask; extra == "flask"
Provides-Extra: opencensus
Requires-Dist: opencensus; extra == "opencensus"
Provides-Extra: opentelemetry
Requires-Dist: opentelemetry-api~=1.0; extra == "opentelemetry"
Provides-Extra: psycopg2
Requires-Dist: psycopg2; extra == "psycopg2"
Provides-Extra: sqlalchemy
Requires-Dist: sqlalchemy; extra == "sqlalchemy"
